MANIFEST.in
setup.cfg
setup.py
dist/tw.lymon-0.1a0dev_20080711-py2.5.egg
docs/conf.py
docs/index.rst
tests/__init__.py
tests/test_widget.py
tw/__init__.py
tw.lymon.egg-info/PKG-INFO
tw.lymon.egg-info/SOURCES.txt
tw.lymon.egg-info/dependency_links.txt
tw.lymon.egg-info/entry_points.txt
tw.lymon.egg-info/namespace_packages.txt
tw.lymon.egg-info/not-zip-safe
tw.lymon.egg-info/paster_plugins.txt
tw.lymon.egg-info/requires.txt
tw.lymon.egg-info/top_level.txt
tw/lymon/__init__.py
tw/lymon/administrar.py
tw/lymon/layout.py
tw/lymon/popup.py
tw/lymon/release.py
tw/lymon/samples.py
tw/lymon/widgets.py
tw/lymon/static/__init__.py
tw/lymon/static/css/__init__.py
tw/lymon/static/css/arrowbullet.png
tw/lymon/static/css/arrowmenu.css
tw/lymon/static/css/arrowmenu.css~
tw/lymon/static/css/colortab.css
tw/lymon/static/css/colortab.css~
tw/lymon/static/css/container.css
tw/lymon/static/css/container.css~
tw/lymon/static/css/gray_menu.css~
tw/lymon/static/css/menu14.gif
tw/lymon/static/css/menu15.gif
tw/lymon/static/css/navigation.css~
tw/lymon/static/css/page_index.css
tw/lymon/static/css/page_index.css~
tw/lymon/static/css/sidebar_center.jpg
tw/lymon/static/css/sidebar_left.jpg
tw/lymon/static/css/sidebar_right.jpg
tw/lymon/static/css/styled_menu.css
tw/lymon/static/css/styled_menu.css~
tw/lymon/static/css/styled_table.css
tw/lymon/static/css/titlebar.png
tw/lymon/static/css/images/__init__.py
tw/lymon/static/css/images/bg_header.jpg
tw/lymon/static/css/images/bullet1.gif
tw/lymon/static/css/images/bullet2.gif
tw/lymon/static/css/layout/__init__,py
tw/lymon/static/css/layout/ad.gif
tw/lymon/static/css/layout/arrow.gif
tw/lymon/static/css/layout/bar.gif
tw/lymon/static/css/layout/bigimage.gif
tw/lymon/static/css/layout/corner.gif
tw/lymon/static/css/layout/dotted.gif
tw/lymon/static/css/layout/image.gif
tw/lymon/static/css/layout/input.gif
tw/lymon/static/css/layout/searchbg.gif
tw/lymon/static/css/layout/style.css
tw/lymon/static/css/layout/style.css~
tw/lymon/static/css/layout/submit.gif
tw/lymon/static/css/popup/__init__.py
tw/lymon/static/css/popup/popup.css
tw/lymon/static/css/popup/popup.css~
tw/lymon/static/css/popup/popup_link.css
tw/lymon/static/css/popup/popup_link.css~
tw/lymon/static/images/__init__.py
tw/lymon/static/images/arrowbullet.png
