Metadata-Version: 1.0
Name: tw.lymon
Version: 0.1a0dev-20080711
Summary: Lymon Widgets
Home-page: UNKNOWN
Author: Laureano Arcanio
Author-email: laureano.arcanio@gmail.com
License: UNKNOWN
Keywords: toscawidgets.widgets
Platform: UNKNOWN
Classifier: Development Status :: 3 - Alpha
Classifier: Environment :: Web Environment
Classifier: Environment :: Web Environment :: ToscaWidgets
Classifier: Topic :: Software Development :: Libraries :: Python Modules
Classifier: Topic :: Software Development :: Widget Sets
Classifier: Intended Audience :: Developers
Classifier: Operating System :: OS Independent
Classifier: Programming Language :: Python
